CHANGELOG.txt
LICENSE.txt
MANIFEST.in
README.rst
setup.py
clippings/__init__.py
clippings/admin.py
clippings/models.py
clippings/tests.py
clippings/locale/en/LC_MESSAGES/django.po
clippings/templatetags/__init__.py
clippings/templatetags/clippings_tags.py
django_cms_clippings.egg-info/PKG-INFO
django_cms_clippings.egg-info/SOURCES.txt
django_cms_clippings.egg-info/dependency_links.txt
django_cms_clippings.egg-info/requires.txt
django_cms_clippings.egg-info/top_level.txt
requirements/base.txt
requirements/test.txt