Metadata-Version: 1.1
Name: django-cms-clippings
Version: 0.1
Summary: Include editable content in applications integrated with django-cms sites.
Home-page: http://pypi.python.org/pypi/django-cms-clippings/
Author: Stuart MacKay
Author-email: smackay@flagstonesoftware.com
License: GPL
Keywords: django,cms,editable,content,plugins
Platform: UNKNOWN
Classifier: Development Status :: 3 - Alpha
Classifier: Environment :: Console
Classifier: Intended Audience :: Science/Research
Classifier: License :: OSI Approved :: GNU General Public License v3 (GPLv3)
Classifier: Operating System :: OS Independent
Classifier: Programming Language :: Python
Classifier: Natural Language :: English
Classifier: Framework :: Django
